Bel_messenger_server-0.1.0.data/scripts/server_run
server/__init__.py
server/server_app.py
server/common/__init__.py
server/common/decos.py
server/common/descrptrs.py
server/common/errors.py
server/common/metaclasses.py
server/common/utils.py
server/common/variables.py
server/log/__init__.py
server/log/client_log_config.py
server/log/server_log_config.py
server/server/__init__.py
server/server/dialog_add_user.py
server/server/dialog_config.py
server/server/dialog_remove_user.py
server/server/main_window.py
server/server/server_core.py
server/server/server_db.py
server/server/stat_window.py
server/unit_tests/__init__.py
server/unit_tests/test_client.py
server/unit_tests/test_server.py
server/unit_tests/test_utils.py
Bel_messenger_server-0.1.0.dist-info/METADATA
Bel_messenger_server-0.1.0.dist-info/WHEEL
Bel_messenger_server-0.1.0.dist-info/top_level.txt
Bel_messenger_server-0.1.0.dist-info/RECORD
